distbot/AssistantLibrary.py
distbot/__init__.py
distbot/__main__.py
distbot/tasksdb.py
robotframework_distbot-1.0.data/scripts/distbot
robotframework_distbot-1.0.data/scripts/distbot.bat
robotframework_distbot-1.0.dist-info/LICENSE
robotframework_distbot-1.0.dist-info/METADATA
robotframework_distbot-1.0.dist-info/WHEEL
robotframework_distbot-1.0.dist-info/top_level.txt
robotframework_distbot-1.0.dist-info/RECORD
