Metadata-Version: 2.1
Name: robotframework-distbot
Version: 1.0
Summary: Distributed test executor for Robot Framework
Home-page: https://github.com/rajeevnaikte/distbot
Author: Rajeev Naik
Author-email: rajeevnaikte@gmail.com
License: Apache License, Version 2.0
Download-URL: https://pypi.python.org/pypi/robotframework-distbot
Platform: UNKNOWN
Classifier: Intended Audience :: Developers
Classifier: Natural Language :: English
Classifier: Programming Language :: Python :: 2.7
Classifier: Programming Language :: Python :: 3
Classifier: Topic :: Software Development :: Testing
Classifier: License :: OSI Approved :: Apache Software License
Classifier: Development Status :: 5 - Production/Stable
Classifier: Framework :: Robot Framework
License-File: LICENSE
Requires-Dist: robotframework
Requires-Dist: psutil
